odoo/addons/l10n_it_withholding_tax/README.rst
odoo/addons/l10n_it_withholding_tax/__init__.py
odoo/addons/l10n_it_withholding_tax/__manifest__.py
odoo/addons/l10n_it_withholding_tax/i18n/it.po
odoo/addons/l10n_it_withholding_tax/i18n/l10n_it_withholding_tax.pot
odoo/addons/l10n_it_withholding_tax/models/__init__.py
odoo/addons/l10n_it_withholding_tax/models/account.py
odoo/addons/l10n_it_withholding_tax/models/withholding_tax.py
odoo/addons/l10n_it_withholding_tax/readme/CONTRIBUTORS.rst
odoo/addons/l10n_it_withholding_tax/readme/DESCRIPTION.rst
odoo/addons/l10n_it_withholding_tax/readme/USAGE.rst
odoo/addons/l10n_it_withholding_tax/security/ir.model.access.csv
odoo/addons/l10n_it_withholding_tax/security/security.xml
odoo/addons/l10n_it_withholding_tax/static/description/icon.png
odoo/addons/l10n_it_withholding_tax/static/description/index.html
odoo/addons/l10n_it_withholding_tax/static/img/fattura-fornitore-768x517.png
odoo/addons/l10n_it_withholding_tax/static/img/foto-3-1-1024x505.png
odoo/addons/l10n_it_withholding_tax/static/img/ritenuta-acconto-odoo-codifica-768x457.png
odoo/addons/l10n_it_withholding_tax/static/src/xml/account_payment.xml
odoo/addons/l10n_it_withholding_tax/tests/__init__.py
odoo/addons/l10n_it_withholding_tax/tests/test_withholding_tax.py
odoo/addons/l10n_it_withholding_tax/views/account.xml
odoo/addons/l10n_it_withholding_tax/views/report_invoice.xml
odoo/addons/l10n_it_withholding_tax/views/withholding_tax.xml
odoo12_addon_l10n_it_withholding_tax-12.0.2.1.7.dist-info/METADATA
odoo12_addon_l10n_it_withholding_tax-12.0.2.1.7.dist-info/WHEEL
odoo12_addon_l10n_it_withholding_tax-12.0.2.1.7.dist-info/top_level.txt
odoo12_addon_l10n_it_withholding_tax-12.0.2.1.7.dist-info/RECORD
