Metadata-Version: 2.1
Name: odoo12-addon-l10n-it-withholding-tax
Version: 12.0.2.1.7
Summary: ITA - Ritenute d'acconto
Home-page: https://github.com/OCA/l10n-italy/tree/12.0/l10n_it_withholding_tax
Author: Openforce, Odoo Italia Network, Odoo Community Association (OCA)
Author-email: support@odoo-community.org
License: AGPL-3
Platform: UNKNOWN
Classifier: Programming Language :: Python
Classifier: Framework :: Odoo
Classifier: Framework :: Odoo :: 12.0
Classifier: License :: OSI Approved :: GNU Affero General Public License v3
Requires-Python: >=3.5
Requires-Dist: odoo12-addon-l10n-it-fatturapa
Requires-Dist: odoo <12.1dev,>=12.0a
